[
  {
    "noteId": 1739601670914,
    "Question": "The Musi and Bhima are tributaries of the river ...............",
    "OP1": "Brahmaputra",
    "OP2": "Mahanadi",
    "OP3": "Krishna",
    "OP4": "Kaveri",
    "Answer": "3",
    "Extra": "",
    "tags": [
      "Geography",
      "GK",
      "Prelims-1"
    ]
  },
  {
    "noteId": 1739601670919,
    "Question": "Sundari, a well known species of trees, is found in:",
    "OP1": "himalayan mountains",
    "OP2": "tropical deciduous forests",
    "OP3": "mangrove forests",
    "OP4": "tropical rainforests",
    "Answer": "3",
    "Extra": "",
    "tags": [
      "Geography",
      "GK",
      "Prelims-1"
    ]
  },
  {
    "noteId": 1739601670927,
    "Question": "Which of the following is mined in the Badampahar mines of Odisha?",
    "OP1": "Dolomite",
    "OP2": "Azurite",
    "OP3": "Hematite",
    "OP4": "Bauxite",
    "Answer": "3",
    "Extra": "",
    "tags": [
      "Geography",
      "GK",
      "Prelims-1"
    ]
  },
  {
    "noteId": 1739601670945,
    "Question": "Name the pass in Uttarakhand which is used by pilgrims to Kailash-Mansarovar Yatra.",
    "OP1": "Khardung La",
    "OP2": "Pensi La",
    "OP3": "Banihal Pass",
    "OP4": "Lipu Lekh",
    "Answer": "4",
    "Extra": "",
    "tags": [
      "Geography",
      "GK",
      "Prelims-2"
    ]
  },
  {
    "noteId": 1739601670950,
    "Question": "Which of the following Biosphere Reserves was the first to be established by the Government of India?",
    "OP1": "Sundarbans Biosphere Reserve",
    "OP2": "Nilgiri Biosphere Reserve",
    "OP3": "Gulf of Mannar Biosphere Reserve",
    "OP4": "Nanda Devi Biosphere Reserve",
    "Answer": "2",
    "Extra": "",
    "tags": [
      "Geography",
      "GK",
      "Prelims-2"
    ]
  },
  {
    "noteId": 1739601670964,
    "Question": "Baglihar Dam is constructed on which river?",
    "OP1": "Chenab",
    "OP2": "Sutlej",
    "OP3": "Indus",
    "OP4": "Ravi",
    "Answer": "1",
    "Extra": "",
    "tags": [
      "Geography",
      "GK",
      "Prelims-3"
    ]
  },
  {
    "noteId": 1739601670969,
    "Question": "In which of the following states, is the Nanda Devi peak located?",
    "OP1": "Jammu and Kashmir",
    "OP2": "Sikkim",
    "OP3": "Assam",
    "OP4": "Uttarakhand",
    "Answer": "4",
    "Extra": "",
    "tags": [
      "Geography",
      "GK",
      "Prelims-3"
    ]
  },
  {
    "noteId": 1739601670976,
    "Question": "‘Mithun’, a cattle breed is found in ______.",
    "OP1": "Tamilnadu",
    "OP2": "Arunachal Pradesh",
    "OP3": "Maharashtra",
    "OP4": "Kerala",
    "Answer": "2",
    "Extra": "",
    "tags": [
      "Geography",
      "GK",
      "Prelims-3"
    ]
  },
  {
    "noteId": 1739601670982,
    "Question": "________, which connects Sikkim with Tibet, was closed after the Chinese aggression on India in 1962 but was reopened in 2006 as the governments of the two countries decided to enhance their trade through land routes.",
    "OP1": "Lanak La",
    "OP2": "Imis La",
    "OP3": "Pensi La",
    "OP4": "Nathu La",
    "Answer": "4",
    "Extra": "",
    "tags": [
      "Geography",
      "GK",
      "Prelims-4"
    ]
  },
  {
    "noteId": 1739601670984,
    "Question": "Where is the Bandipur National Park located?",
    "OP1": "Gujarat",
    "OP2": "Sikkim",
    "OP3": "Karnataka",
    "OP4": "Kerala",
    "Answer": "3",
    "Extra": "",
    "tags": [
      "Geography",
      "GK",
      "Prelims-4"
    ]
  },
  {
    "noteId": 1739601671001,
    "Question": "World ............... Day 2025 was observed on 22nd March with the theme ‘Glacier Preservation’",
    "OP1": "Water",
    "OP2": "Forest",
    "OP3": "Environment",
    "OP4": "Petroleum",
    "Answer": "1",
    "Extra": "",
    "tags": [
      "Geography",
      "GK",
      "Prelims-4"
    ]
  },
  {
    "noteId": 1739601671010,
    "Question": "Which of the following passes connects Tawang with Lhasa?",
    "OP1": "Bum La Pass",
    "OP2": "Chankan Pass",
    "OP3": "Kumjawng Pass",
    "OP4": "Hpungan Pass",
    "Answer": "1",
    "Extra": "",
    "tags": [
      "Geography",
      "GK",
      "Prelims-5"
    ]
  },
  {
    "noteId": 1739601671013,
    "Question": "Which of the following passes is known as the gateway connecting Jammu and Srinagar?",
    "OP1": "Lanak-La Pass",
    "OP2": "Chang-La Pass",
    "OP3": "Banihal Pass",
    "OP4": "Aghil Pass",
    "Answer": "3",
    "Extra": "",
    "tags": [
      "Geography",
      "GK",
      "Prelims-5"
    ]
  },
  {
    "noteId": 1739601671019,
    "Question": "Majuli, the largest river island in the world is located in ________.",
    "OP1": "Uttar Pradesh",
    "OP2": "Assam",
    "OP3": "Nagaland",
    "OP4": "Arunachal Pradesh",
    "Answer": "2",
    "Extra": "",
    "tags": [
      "Geography",
      "GK",
      "Prelims-5"
    ]
  },
  {
    "noteId": 1739601671025,
    "Question": "......... in Himachal Pradesh is a famous tourist attraction.",
    "OP1": "Rohtang Pass",
    "OP2": "Mintaka Pass",
    "OP3": "Chang-La Pass",
    "OP4": "Aghil Pass",
    "Answer": "1",
    "Extra": "",
    "tags": [
      "Geography",
      "GK",
      "Prelims-5"
    ]
  },
  {
    "noteId": 1739601671035,
    "Question": "......... is the largest river island in the world.",
    "OP1": "Munroe",
    "OP2": "Majuli",
    "OP3": "Bahvani",
    "OP4": "Umananda",
    "Answer": "2",
    "Extra": "",
    "tags": [
      "Geography",
      "GK",
      "Prelims-6"
    ]
  },
  {
    "noteId": 1739601671036,
    "Question": "Varkala, Chowara, Chavakkad and Nattika are beaches in the state of ..........",
    "OP1": "Karnataka",
    "OP2": "Tamil Nadu",
    "OP3": "Kerala",
    "OP4": "Maharashtra",
    "Answer": "3",
    "Extra": "",
    "tags": [
      "Geography",
      "GK",
      "Prelims-6"
    ]
  },
  {
    "noteId": 1739601671044,
    "Question": "The highest railway station in India is located in the state of .............",
    "OP1": "Sikkim",
    "OP2": "Uttar Pradesh",
    "OP3": "West Bengal",
    "OP4": "Nagaland",
    "Answer": "3",
    "Extra": "",
    "tags": [
      "Geography",
      "GK",
      "Prelims-6"
    ]
  },
  {
    "noteId": 1739601671063,
    "Question": "Which city in India is the least populated according to the 2011 census?",
    "OP1": "Datia",
    "OP2": "Banswara",
    "OP3": "Nagda",
    "OP4": "Kapurthala",
    "Answer": "4",
    "Extra": "",
    "tags": [
      "Geography",
      "GK",
      "Prelims-7"
    ]
  },
  {
    "noteId": 1739601671071,
    "Question": "The Vivekananda Rock Memorial is located in ............",
    "OP1": "Ladakh",
    "OP2": "Andaman",
    "OP3": "Kanyakumari",
    "OP4": "Srinagar",
    "Answer": "3",
    "Extra": "",
    "tags": [
      "Geography",
      "GK",
      "Prelims-7"
    ]
  },
  {
    "noteId": 1739601671089,
    "Question": "Name the longest river in Asia.",
    "OP1": "Amazon",
    "OP2": "Yenisei",
    "OP3": "Nile",
    "OP4": "Yangtze",
    "Answer": "4",
    "Extra": "",
    "tags": [
      "Geography",
      "GK",
      "Prelims-8"
    ]
  },
  {
    "noteId": 1739601671093,
    "Question": "Which river passes through maximum number of countries?",
    "OP1": "Volga",
    "OP2": "Rhine",
    "OP3": "Amazon",
    "OP4": "Danube",
    "Answer": "4",
    "Extra": "",
    "tags": [
      "Geography",
      "GK",
      "Prelims-8"
    ]
  },
  {
    "noteId": 1739601671098,
    "Question": "Which of the following is the longest rivers in India?",
    "OP1": "Brahmaputra",
    "OP2": "Godavari",
    "OP3": "Ganga",
    "OP4": "Kaveri",
    "Answer": "3",
    "Extra": "",
    "tags": [
      "Geography",
      "GK",
      "Prelims-8"
    ]
  },
  {
    "noteId": 1739601671110,
    "Question": "............ is an important road link between Srinagar on one side and Kargil and Leh on the other side.",
    "OP1": "Zoji La",
    "OP2": "Qara Tag La",
    "OP3": "Muling La",
    "OP4": "Shipki La",
    "Answer": "1",
    "Extra": "",
    "tags": [
      "Geography",
      "GK",
      "Prelims-9"
    ]
  },
  {
    "noteId": 1739601671133,
    "Question": "............. Strait separates the islands of Java (east) and Sumatra.",
    "OP1": "Yucatan",
    "OP2": "Sunda",
    "OP3": "Cook",
    "OP4": "Malacca",
    "Answer": "2",
    "Extra": "",
    "tags": [
      "Geography",
      "GK",
      "Prelims-10"
    ]
  },
  {
    "noteId": 1739601671135,
    "Question": "............. pass connects Uttarakhand and Tibet and is situated in the north of Gangotri.",
    "OP1": "Shipki La",
    "OP2": "Muling La",
    "OP3": "Zoji La",
    "OP4": "Bara Lacha La",
    "Answer": "2",
    "Extra": "",
    "tags": [
      "Geography",
      "GK",
      "Prelims-10"
    ]
  },
  {
    "noteId": 1739601671159,
    "Question": "Silent Valley National Park is located in the Indian state of .............",
    "OP1": "Uttarakhand",
    "OP2": "Kerala",
    "OP3": "Madhya Pradesh",
    "OP4": "West Bengal",
    "Answer": "2",
    "Extra": "",
    "tags": [
      "Geography",
      "GK",
      "Prelims-11"
    ]
  },
  {
    "noteId": 1739601671166,
    "Question": "Which of the following Indian islands lies in the Bay of Bengal?",
    "OP1": "Diu",
    "OP2": "Andaman and Nicobar",
    "OP3": "Daman",
    "OP4": "Lakshadweep",
    "Answer": "2",
    "Extra": "",
    "tags": [
      "Geography",
      "GK",
      "Prelims-11"
    ]
  },
  {
    "noteId": 1739601671174,
    "Question": "What is the geographic name given to a deep and narrow valley consisting of steep sides created by weathering and erosion by rivers, wind, rain and tectonic activity?",
    "OP1": "Ridge",
    "OP2": "Buttes",
    "OP3": "Basin",
    "OP4": "Canyon",
    "Answer": "4",
    "Extra": "",
    "tags": [
      "Geography",
      "GK",
      "Prelims-11"
    ]
  },
  {
    "noteId": 1739601671190,
    "Question": "Which of the following is the busiest sea port in Pakistan?",
    "OP1": "Port of Qasim",
    "OP2": "Port of Keti",
    "OP3": "Gwadar Port",
    "OP4": "Port of Karachi",
    "Answer": "4",
    "Extra": "",
    "tags": [
      "Geography",
      "GK",
      "Prelims-12"
    ]
  },
  {
    "noteId": 1739601671193,
    "Question": "What is the term used to describe the angular distance of a place north or south of Earth's equator?",
    "OP1": "Pole",
    "OP2": "Latitude",
    "OP3": "Hemisphere",
    "OP4": "Longitude",
    "Answer": "2",
    "Extra": "",
    "tags": [
      "Geography",
      "GK",
      "Prelims-12"
    ]
  },
  {
    "noteId": 1739601671209,
    "Question": "Fertile riverine alluvial soil is best suited for producing ..............",
    "OP1": "Corn",
    "OP2": "cotton",
    "OP3": "rice",
    "OP4": "tea",
    "Answer": "3",
    "Extra": "",
    "tags": [
      "Geography",
      "GK",
      "Prelims-13"
    ]
  },
  {
    "noteId": 1739601671230,
    "Question": "The 'Diphu Pass' which is the tri-junction between India, Myanmar and China is on this Border Line?",
    "OP1": "Durand Line",
    "OP2": "Radcliffe Line",
    "OP3": "McMahon Line",
    "OP4": "Palk Strait",
    "Answer": "3",
    "Extra": "",
    "tags": [
      "Geography",
      "GK",
      "Prelims-14"
    ]
  },
  {
    "noteId": 1739601671233,
    "Question": "Which of the following is the 6th highest waterfall in India?",
    "OP1": "Courtallam Falls",
    "OP2": "Agaya Gangai",
    "OP3": "Suruli Falls",
    "OP4": "Thalaiyar Falls",
    "Answer": "4",
    "Extra": "",
    "tags": [
      "Geography",
      "GK",
      "Prelims-14"
    ]
  },
  {
    "noteId": 1739601671239,
    "Question": "Daringbadi hill station is located in the Indian state of ...............",
    "OP1": "West Bengal",
    "OP2": "Kerala",
    "OP3": "Odisha",
    "OP4": "Maharashtra",
    "Answer": "3",
    "Extra": "",
    "tags": [
      "Geography",
      "GK",
      "Prelims-14"
    ]
  },
  {
    "noteId": 1739601671259,
    "Question": "The 'Friendship Highway' is a road that connects China to ..........",
    "OP1": "Myanmar",
    "OP2": "Pakistan",
    "OP3": "India",
    "OP4": "Nepal",
    "Answer": "4",
    "Extra": "",
    "tags": [
      "Geography",
      "GK",
      "Prelims-15"
    ]
  },
  {
    "noteId": 1739601671261,
    "Question": "In which province of China is the Huangguoshu National Park located which houses the world's largest waterfall cluster.",
    "OP1": "Shandon",
    "OP2": "Guizhou",
    "OP3": "Yunnan",
    "OP4": "Jiangsu",
    "Answer": "2",
    "Extra": "",
    "tags": [
      "Geography",
      "GK",
      "Prelims-15"
    ]
  },
  {
    "noteId": 1739601671277,
    "Question": "Which one of the following is the highest altitude lake of Pakistan?",
    "OP1": "Rush Lake",
    "OP2": "Satpara Lake",
    "OP3": "Paristan Lake",
    "OP4": "Attabad Lake",
    "Answer": "1",
    "Extra": "",
    "tags": [
      "Geography",
      "GK",
      "Prelims-15"
    ]
  },
  {
    "noteId": 1739601671279,
    "Question": "Which state of India has the longest mainland coastline?",
    "OP1": "Gujarat",
    "OP2": "Maharashtra",
    "OP3": "Kerala",
    "OP4": "Odisha",
    "Answer": "1",
    "Extra": "",
    "tags": [
      "Geography",
      "GK",
      "Prelims-16"
    ]
  },
  {
    "noteId": 1739601671283,
    "Question": "Which of the following is the highest mountain peak in Maharashtra?",
    "OP1": "Anjaneri",
    "OP2": "Taramati",
    "OP3": "Salher",
    "OP4": "Kalsubai Shikhar",
    "Answer": "4",
    "Extra": "",
    "tags": [
      "Geography",
      "GK",
      "Prelims-16"
    ]
  },
  {
    "noteId": 1739601671296,
    "Question": "Which of the following countries is the largest producer of wheat in the world?",
    "OP1": "Bangladesh",
    "OP2": "India",
    "OP3": "Myanmar (Burma)",
    "OP4": "China",
    "Answer": "4",
    "Extra": "",
    "tags": [
      "Geography",
      "GK",
      "Prelims-16"
    ]
  },
  {
    "noteId": 1739601671306,
    "Question": "The river Ganga emerges from Gangotri Glacier and ends at ............",
    "OP1": "Pacific Ocean",
    "OP2": "Arabian Sea",
    "OP3": "Bay of Bengal",
    "OP4": "Indian Ocean",
    "Answer": "3",
    "Extra": "",
    "tags": [
      "Geography",
      "GK",
      "Prelims-17"
    ]
  },
  {
    "noteId": 1739601671319,
    "Question": "Which country in the world has the largest number of international borders?",
    "OP1": "Nepal",
    "OP2": "India",
    "OP3": "China",
    "OP4": "Pakistan",
    "Answer": "3",
    "Extra": "",
    "tags": [
      "Geography",
      "GK",
      "Prelims-17"
    ]
  },
  {
    "noteId": 1739601671336,
    "Question": "Which one of the following is the deepest gorge in the world?",
    "OP1": "Garganta del Cares",
    "OP2": "Kali Gandaki Gorge",
    "OP3": "Vikos Gorge",
    "OP4": "Tiger Leaping Gorge",
    "Answer": "2",
    "Extra": "",
    "tags": [
      "Geography",
      "GK",
      "Prelims-18"
    ]
  },
  {
    "noteId": 1739601671350,
    "Question": "How many provinces are there in Sri Lanka?",
    "OP1": "8",
    "OP2": "9",
    "OP3": "11",
    "OP4": "6",
    "Answer": "2",
    "Extra": "",
    "tags": [
      "Geography",
      "GK",
      "Prelims-18"
    ]
  },
  {
    "noteId": 1739601671352,
    "Question": "Which of the following is the longest river in Pakistan that originates from Lake Manasarovar?",
    "OP1": "Sutlej",
    "OP2": "Kabul",
    "OP3": "Indus",
    "OP4": "Chenab",
    "Answer": "3",
    "Extra": "",
    "tags": [
      "Geography",
      "GK",
      "Prelims-18"
    ]
  },
  {
    "noteId": 1739601671361,
    "Question": "Identify the element that is most prolific in the crust of the earth.",
    "OP1": "Iron",
    "OP2": "Silicon",
    "OP3": "Hydrogen",
    "OP4": "Oxygen",
    "Answer": "4",
    "Extra": "",
    "tags": [
      "Geography",
      "GK",
      "Prelims-19"
    ]
  },
  {
    "noteId": 1739601671363,
    "Question": "The easternmost point of India is .............",
    "OP1": "Doulchara",
    "OP2": "Mokokchung",
    "OP3": "Kibithu",
    "OP4": "Wokha",
    "Answer": "3",
    "Extra": "",
    "tags": [
      "Geography",
      "GK",
      "Prelims-19"
    ]
  },
  {
    "noteId": 1739601671364,
    "Question": "Which of the following is called the 'Grand Canyon of India'?",
    "OP1": "Laitlum Canyon",
    "OP2": "Gangani Grand Canyon",
    "OP3": "Great Canyon of Gandikota",
    "OP4": "Chambal River Canyon",
    "Answer": "3",
    "Extra": "",
    "tags": [
      "Geography",
      "GK",
      "Prelims-19"
    ]
  },
  {
    "noteId": 1739601671373,
    "Question": "In which of the following states is the 'Lusei' dialect spoken?",
    "OP1": "Kerala",
    "OP2": "Goa",
    "OP3": "Mizoram",
    "OP4": "Manipur",
    "Answer": "3",
    "Extra": "",
    "tags": [
      "Geography",
      "GK",
      "Prelims-19"
    ]
  }
]